mercury/dataschema/__init__.py
mercury/dataschema/anonymize.py
mercury/dataschema/calculator.py
mercury/dataschema/create_tutorials.py
mercury/dataschema/feature.py
mercury/dataschema/schemagen.py
mercury/dataschema/tutorials/hello_dataschema.ipynb
mercury_dataschema-1.1.2.dist-info/LICENSE
mercury_dataschema-1.1.2.dist-info/METADATA
mercury_dataschema-1.1.2.dist-info/WHEEL
mercury_dataschema-1.1.2.dist-info/top_level.txt
mercury_dataschema-1.1.2.dist-info/RECORD
