Metadata-Version: 2.2
Name: mercury-dataschema
Version: 1.1.2
Summary: Mercury's DataSchema package allows the automatic recognition and validation of feature types.
Author-email: Mercury Team <mercury.group@bbva.com>
Project-URL: Homepage, https://github.com/BBVA/mercury-dataschema
Project-URL: Bug Tracker, https://github.com/BBVA/mercury-dataschema/issues
Classifier: Programming Language :: Python :: 3
Classifier: License :: OSI Approved :: Apache Software License
Classifier: Operating System :: OS Independent
Requires-Python: >=3.7
License-File: LICENSE
Requires-Dist: numpy
Requires-Dist: cryptography
Provides-Extra: dev
Requires-Dist: seaborn; extra == "dev"
Requires-Dist: pytest; extra == "dev"
Requires-Dist: flake8; extra == "dev"
Provides-Extra: doc
Requires-Dist: mkdocs; extra == "doc"
Requires-Dist: mkdocstrings[python]; extra == "doc"
Requires-Dist: mkdocs-material; extra == "doc"
Requires-Dist: mkdocs-minify-plugin==0.5.0; extra == "doc"
Requires-Dist: mkdocs-exclude; extra == "doc"
Requires-Dist: nbconvert; extra == "doc"
